oua_auth/__init__.py
oua_auth/admin.py
oua_auth/apps.py
oua_auth/authentication.py
oua_auth/backend.py
oua_auth/logging_init.py
oua_auth/logging_utils.py
oua_auth/middleware.py
oua_auth/models.py
oua_auth/security_middleware.py
oua_auth/token_blacklist.py
oua_auth/management/__init__.py
oua_auth/management/commands/__init__.py
oua_auth/management/commands/clean_expired_tokens.py
oua_auth/migrations/0001_initial.py
oua_auth/migrations/0002_suspicious_activity_and_user_security.py
oua_auth/migrations/__init__.py
oua_auth-0.3.0.dist-info/licenses/LICENSE
tests/__init__.py
tests/conftest.py
tests/settings.py
tests/test_admin.py
tests/test_admin_integration.py
tests/test_api_integration.py
tests/test_apps.py
tests/test_authentication.py
tests/test_authentication_admin.py
tests/test_authentication_extended.py
tests/test_backend.py
tests/test_command_clean_expired_tokens.py
tests/test_integration.py
tests/test_logging.py
tests/test_logging_init.py
tests/test_logging_utils.py
tests/test_middleware.py
tests/test_middleware_integration.py
tests/test_security_middleware.py
tests/test_token_blacklist.py
tests/test_token_blacklist_memory.py
tests/test_user_security_profile.py
tests/urls.py
oua_auth-0.3.0.dist-info/METADATA
oua_auth-0.3.0.dist-info/WHEEL
oua_auth-0.3.0.dist-info/top_level.txt
oua_auth-0.3.0.dist-info/RECORD
